faker_bill/__init__.py
faker_bill/fa_IR/__init__.py
faker_bill-0.1.1.dist-info/LICENSE
faker_bill-0.1.1.dist-info/METADATA
faker_bill-0.1.1.dist-info/WHEEL
faker_bill-0.1.1.dist-info/top_level.txt
faker_bill-0.1.1.dist-info/RECORD
